LICENSE
README.md
setup.py
hdcLib/__init__.py
hdcLib/functional.py
hdcLib/utils.py
hdcLib.egg-info/PKG-INFO
hdcLib.egg-info/SOURCES.txt
hdcLib.egg-info/dependency_links.txt
hdcLib.egg-info/not-zip-safe
hdcLib.egg-info/top_level.txt