Metadata-Version: 2.1
Name: hdcLib
Version: 0.1
Summary: A python library for hyperdimensional computing
Home-page: https://github.com/mikeheddes/hdc-lib
License: MIT
Platform: UNKNOWN
License-File: LICENSE
